morpho_typing/__init__.py
morpho_typing/types.py
morpho_typing-1.5.0.dist-info/METADATA
morpho_typing-1.5.0.dist-info/WHEEL
morpho_typing-1.5.0.dist-info/licenses/LICENSE
morpho_typing-1.5.0.dist-info/RECORD
