Metadata-Version: 2.3
Name: morpho-typing
Version: 1.5.0
Summary: Provides type validation for arbitrarily defined, extendible JSON-style Schema definitions. Part of the Morpho Design Explorer Project.
Project-URL: Homepage, https://github.com/MorphoDesignExplorer/morpho-typing/
Author-email: Krishna Sivakumar <krishnasivaprogrammer@gmail.com>
License-File: LICENSE
Classifier: License :: OSI Approved :: MIT License
Classifier: Operating System :: OS Independent
Classifier: Programming Language :: Python :: 3
Requires-Python: >=3.8
Requires-Dist: pydantic==2.6.4
